simplenet/__init__.py
simplenet/simplenet.py
simplenet-0.1.4.dist-info/LICENSE
simplenet-0.1.4.dist-info/METADATA
simplenet-0.1.4.dist-info/WHEEL
simplenet-0.1.4.dist-info/top_level.txt
simplenet-0.1.4.dist-info/RECORD
