Metadata-Version: 2.1
Name: simplenet
Version: 0.1.4
Summary: A simple neural network in Python
Home-page: https://github.com/n8henrie/simplenet
Author: Nathan Henrie
Author-email: nate@n8henrie.com
License: MIT
Keywords: simplenet
Classifier: Programming Language :: Python :: 3
Classifier: Programming Language :: Python :: 3.8
Classifier: Programming Language :: Python :: 3.9
Classifier: Programming Language :: Python :: 3.10
License-File: LICENSE
Requires-Dist: numpy (==1.22.4)
Provides-Extra: dev
Requires-Dist: build (==0.8.0) ; extra == 'dev'
Requires-Dist: docutils (==0.14) ; extra == 'dev'
Requires-Dist: pypandoc (==1.8.1) ; extra == 'dev'
Requires-Dist: recommonmark (==0.7.1) ; extra == 'dev'
Requires-Dist: sphinx-rtd-theme (==1.0.0) ; extra == 'dev'
Requires-Dist: Sphinx (==5.0.2) ; extra == 'dev'
Requires-Dist: twine (==4.0.1) ; extra == 'dev'
Provides-Extra: test
Requires-Dist: black (==22.3.0) ; extra == 'test'
Requires-Dist: flake8-docstrings (==1.6.0) ; extra == 'test'
Requires-Dist: flake8-import-order (==0.18.1) ; extra == 'test'
Requires-Dist: mypy (==0.961) ; extra == 'test'
Requires-Dist: pep8-naming (==0.13.0) ; extra == 'test'
Requires-Dist: pylint (==2.14.3) ; extra == 'test'
Requires-Dist: pytest (==7.1.2) ; extra == 'test'
Requires-Dist: tox (==3.25.0) ; extra == 'test'
Requires-Dist: tensorflow-macos (==2.9.1) ; (platform_system == "Darwin") and extra == 'test'
Requires-Dist: tensorflow-cpu (==2.9.1) ; (platform_system == "Linux") and extra == 'test'
